fso_metadata/__init__.py
fso_metadata/api_call.py
fso_metadata/api_class.py
fso_metadata/constants.py
fso_metadata/format_request.py
fso_metadata-0.8.3.dist-info/LICENSE.txt
fso_metadata-0.8.3.dist-info/METADATA
fso_metadata-0.8.3.dist-info/WHEEL
fso_metadata-0.8.3.dist-info/top_level.txt
fso_metadata-0.8.3.dist-info/RECORD
