Metadata-Version: 2.1
Name: fso-metadata
Version: 0.8.3
Summary: FSO metadata access automation. Seamless access to SMS 2.0 APIs in Python.
Home-page: https://renkulab.io/gitlab/pauline.maury-laribiere/meatadata-auto
Author: Pauline Maury Laribière, Lancelot Marti
Author-email: pauline.maury-laribiere@bfs.admin.ch, lancelot.marti@bfs.admin.ch
License: MIT
Download-URL: https://renkulab.io/gitlab/pauline.maury-laribiere/meatadata-auto/-/archive/v_0.8/meatadata-auto-v_0.8.tar.gz
Keywords: metadata,automation,open-data,API,SMS 2.0,statistics,IOP
Platform: UNKNOWN
Classifier: Development Status :: 3 - Alpha
Classifier: Intended Audience :: Developers
Classifier: Topic :: Software Development :: Build Tools
Classifier: License :: OSI Approved :: MIT License
Classifier: Programming Language :: Python :: 3
Classifier: Programming Language :: Python :: 3.6
Classifier: Programming Language :: Python :: 3.7
Classifier: Programming Language :: Python :: 3.8
Classifier: Programming Language :: Python :: 3.9
License-File: LICENSE.txt
Requires-Dist: openpyxl
Requires-Dist: pandas
Requires-Dist: pandasdmx
